[
  {
    "id": 0,
    "title": "Day",
    "description": "my description"
  },
  {
    "id": 1,
    "title": "Time",
    "description": "my description Time"
  },
  {
    "id": 2,
    "title": "Hour",
    "description": "my description Hour"
  },
  {
    "id": 3,
    "title": "Minute",
    "description": "my description Minute"
  },
  {
    "id": 4,
    "title": "Second",
    "description": "my description Second"
  },
  {
    "id": 5,
    "title": "Month",
    "description": "my description Month"
  },
  {
    "id": 6,
    "title": "Year",
    "description": "my description Year"
  },
  {
    "id": 7,
    "title": "Monday",
    "description": "my description Monday"
  },
  {
    "id": 8,
    "title": "Tuesday",
    "description": "my description Tuesday"
  },
  {
    "id": 9,
    "title": "Wednesday",
    "description": "my description Monday Wednesday"
  },
  {
    "id": 10,
    "title": "Thursday",
    "description": "my description Thursday"
  }
]